[
  {
    "canonical_video_id": "6978042476519001349",
    "video_url": "https://www.tiktok.com/@ash.thrower/video/6978042476519001349",
    "source": "combined_transcript",
    "confidence": 2,
    "brand_clean": "L'Oréal",
    "product_line_clean": "True Match Nude Hyaluronic Tinted Serum",
    "shade_clean": null,
    "brand_score": 93,
    "product_score": 90,
    "shade_score": 0,
    "shade_variant_used_for_match": null,
    "brand_raw_examples": "L'Oreal",
    "product_line_raw_examples": "True Match",
    "shade_raw_examples": "4.d/4.w",
    "brand_standardized": "L'Oréal Paris",
    "brand_standardized_score": 95,
    "brand_match_status": "success"
  },
  {
    "canonical_video_id": "6991430067905694982",
    "video_url": "https://www.tiktok.com/@jameela.joie/video/6991430067905694982",
    "source": "combined_transcript",
    "confidence": 2,
    "brand_clean": "NARS",
    "product_line_clean": "Natural Radiant Longwear Foundation",
    "shade_clean": null,
    "brand_score": 100,
    "product_score": 95,
    "shade_score": 0,
    "shade_variant_used_for_match": null,
    "brand_raw_examples": "NARS",
    "product_line_raw_examples": "Radiant Longwear Foundation",
    "shade_raw_examples": "Macau",
    "brand_standardized": "NARS",
    "brand_standardized_score": 95,
    "brand_match_status": "success"
  },
  {
    "canonical_video_id": "7096913425695018245",
    "video_url": "https://www.tiktok.com/@hanstluce/video/7096913425695018245",
    "source": "combined_transcript",
    "confidence": 2,
    "brand_clean": "Charlotte Tilbury",
    "product_line_clean": "Beautiful Skin Foundation",
    "shade_clean": null,
    "brand_score": 100,
    "product_score": 90,
    "shade_score": 0,
    "shade_variant_used_for_match": null,
    "brand_raw_examples": "Charlotte Tilbury",
    "product_line_raw_examples": "Beautiful Skin",
    "shade_raw_examples": "6N",
    "brand_standardized": "Charlotte Tilbury",
    "brand_standardized_score": 95,
    "brand_match_status": "success"
  },
  {
    "canonical_video_id": "7096913425695018245",
    "video_url": "https://www.tiktok.com/@hanstluce/video/7096913425695018245",
    "source": "combined_transcript",
    "confidence": 2,
    "brand_clean": "Too Faced",
    "product_line_clean": "Born This Way Ethereal Light Illuminating Smoothing Concealer",
    "shade_clean": null,
    "brand_score": 100,
    "product_score": 90,
    "shade_score": 0,
    "shade_variant_used_for_match": null,
    "brand_raw_examples": "Too Faced",
    "product_line_raw_examples": "Born This Way",
    "shade_raw_examples": "Natural Beige",
    "brand_standardized": "Too Faced",
    "brand_standardized_score": 95,
    "brand_match_status": "success"
  },
  {
    "canonical_video_id": "7096913425695018245",
    "video_url": "https://www.tiktok.com/@hanstluce/video/7096913425695018245",
    "source": "combined_transcript",
    "confidence": 1,
    "brand_clean": "NARS",
    "product_line_clean": null,
    "shade_clean": null,
    "brand_score": 100,
    "product_score": 0,
    "shade_score": 0,
    "shade_variant_used_for_match": null,
    "brand_raw_examples": "NARS",
    "product_line_raw_examples": "",
    "shade_raw_examples": "to hell",
    "brand_standardized": "NARS",
    "brand_standardized_score": 95,
    "brand_match_status": "success"
  },
  {
    "canonical_video_id": "7096913425695018245",
    "video_url": "https://www.tiktok.com/@hanstluce/video/7096913425695018245",
    "source": "combined_transcript",
    "confidence": 3,
    "brand_clean": "L'Oréal",
    "product_line_clean": "True Match Nude Hyaluronic Tinted Serum",
    "shade_clean": "4-5 Medium",
    "brand_score": 93,
    "product_score": 90,
    "shade_score": 90,
    "shade_variant_used_for_match": "425 Medium",
    "brand_raw_examples": "L'Oreal",
    "product_line_raw_examples": "Tinted Serum",
    "shade_raw_examples": "425 Medium",
    "brand_standardized": "L'Oréal Paris",
    "brand_standardized_score": 95,
    "brand_match_status": "success"
  },
  {
    "canonical_video_id": "7096913425695018245",
    "video_url": "https://www.tiktok.com/@hanstluce/video/7096913425695018245",
    "source": "combined_transcript",
    "confidence": 3,
    "brand_clean": "L'Oréal",
    "product_line_clean": "Infallible 24H Fresh Wear Foundation In A Powder",
    "shade_clean": "140 Golden Beige",
    "brand_score": 93,
    "product_score": 85,
    "shade_score": 100,
    "shade_variant_used_for_match": "140 Golden Beige",
    "brand_raw_examples": "L'Oreal",
    "product_line_raw_examples": "Infallible Freshwear",
    "shade_raw_examples": "140 Golden Beige",
    "brand_standardized": "L'Oréal Paris",
    "brand_standardized_score": 95,
    "brand_match_status": "success"
  },
  {
    "canonical_video_id": "7096913425695018245",
    "video_url": "https://www.tiktok.com/@hanstluce/video/7096913425695018245",
    "source": "combined_transcript",
    "confidence": 3,
    "brand_clean": "MAC",
    "product_line_clean": "Studio Fix Every-Wear All-Over Face Concealer Pen",
    "shade_clean": "NC35",
    "brand_score": 100,
    "product_score": 85,
    "shade_score": 90,
    "shade_variant_used_for_match": "C3",
    "brand_raw_examples": "MAC",
    "product_line_raw_examples": "Face and Body",
    "shade_raw_examples": "C3",
    "brand_standardized": "MAC",
    "brand_standardized_score": 95,
    "brand_match_status": "success"
  },
  {
    "canonical_video_id": "7096913425695018245",
    "video_url": "https://www.tiktok.com/@hanstluce/video/7096913425695018245",
    "source": "combined_transcript",
    "confidence": 2,
    "brand_clean": "MAC",
    "product_line_clean": "MAC Studio Fix Fluid SPF15 NC25",
    "shade_clean": null,
    "brand_score": 100,
    "product_score": 90,
    "shade_score": 0,
    "shade_variant_used_for_match": null,
    "brand_raw_examples": "MAC",
    "product_line_raw_examples": "Studio Fix",
    "shade_raw_examples": "NC27",
    "brand_standardized": "MAC",
    "brand_standardized_score": 95,
    "brand_match_status": "success"
  },
  {
    "canonical_video_id": "7096913425695018245",
    "video_url": "https://www.tiktok.com/@hanstluce/video/7096913425695018245",
    "source": "combined_transcript",
    "confidence": 1,
    "brand_clean": null,
    "product_line_clean": null,
    "shade_clean": null,
    "brand_score": 0,
    "product_score": 0,
    "shade_score": 0,
    "shade_variant_used_for_match": null,
    "brand_raw_examples": "Mascara",
    "product_line_raw_examples": "Skinning Base",
    "shade_raw_examples": "SB11",
    "brand_standardized": null,
    "brand_standardized_score": 0,
    "brand_match_status": "ai_returned_none"
  },
  {
    "canonical_video_id": "7096913425695018245",
    "video_url": "https://www.tiktok.com/@hanstluce/video/7096913425695018245",
    "source": "combined_transcript",
    "confidence": 1,
    "brand_clean": null,
    "product_line_clean": null,
    "shade_clean": null,
    "brand_score": 0,
    "product_score": 0,
    "shade_score": 0,
    "shade_variant_used_for_match": null,
    "brand_raw_examples": "ABH",
    "product_line_raw_examples": "Luminous Foundation",
    "shade_raw_examples": "315N",
    "brand_standardized": "Anastasia Beverly Hills",
    "brand_standardized_score": 95,
    "brand_match_status": "success"
  },
  {
    "canonical_video_id": "7096913425695018245",
    "video_url": "https://www.tiktok.com/@hanstluce/video/7096913425695018245",
    "source": "combined_transcript",
    "confidence": 3,
    "brand_clean": "Maybelline",
    "product_line_clean": "Fit Me Dewy + Smooth Foundation",
    "shade_clean": "Sun Beige",
    "brand_score": 100,
    "product_score": 90,
    "shade_score": 85,
    "shade_variant_used_for_match": "222 True Beige",
    "brand_raw_examples": "Maybelline",
    "product_line_raw_examples": "Fit Me",
    "shade_raw_examples": "222 True Beige",
    "brand_standardized": "Maybelline",
    "brand_standardized_score": 95,
    "brand_match_status": "success"
  },
  {
    "canonical_video_id": "7096913425695018245",
    "video_url": "https://www.tiktok.com/@hanstluce/video/7096913425695018245",
    "source": "combined_transcript",
    "confidence": 1,
    "brand_clean": "HUDA BEAUTY",
    "product_line_clean": null,
    "shade_clean": null,
    "brand_score": 100,
    "product_score": 0,
    "shade_score": 0,
    "shade_variant_used_for_match": null,
    "brand_raw_examples": "Huda Beauty",
    "product_line_raw_examples": "",
    "shade_raw_examples": "Latte",
    "brand_standardized": "HUDA BEAUTY",
    "brand_standardized_score": 95,
    "brand_match_status": "success"
  },
  {
    "canonical_video_id": "7096913425695018245",
    "video_url": "https://www.tiktok.com/@hanstluce/video/7096913425695018245",
    "source": "combined_transcript",
    "confidence": 3,
    "brand_clean": "DIOR",
    "product_line_clean": "Backstage Concealer",
    "shade_clean": "3N",
    "brand_score": 100,
    "product_score": 90,
    "shade_score": 100,
    "shade_variant_used_for_match": "3N",
    "brand_raw_examples": "Dior",
    "product_line_raw_examples": "Backstage",
    "shade_raw_examples": "3N",
    "brand_standardized": "DIOR",
    "brand_standardized_score": 95,
    "brand_match_status": "success"
  },
  {
    "canonical_video_id": "7096913425695018245",
    "video_url": "https://www.tiktok.com/@hanstluce/video/7096913425695018245",
    "source": "combined_transcript",
    "confidence": 1,
    "brand_clean": "Makeup Revolution",
    "product_line_clean": null,
    "shade_clean": null,
    "brand_score": 100,
    "product_score": 0,
    "shade_score": 0,
    "shade_variant_used_for_match": null,
    "brand_raw_examples": "Makeup Revolution",
    "product_line_raw_examples": "",
    "shade_raw_examples": "F10",
    "brand_standardized": "Makeup Revolution",
    "brand_standardized_score": 95,
    "brand_match_status": "success"
  },
  {
    "canonical_video_id": "7096913425695018245",
    "video_url": "https://www.tiktok.com/@hanstluce/video/7096913425695018245",
    "source": "combined_transcript",
    "confidence": 1,
    "brand_clean": "GIORGIO ARMANI",
    "product_line_clean": null,
    "shade_clean": null,
    "brand_score": 100,
    "product_score": 0,
    "shade_score": 0,
    "shade_variant_used_for_match": null,
    "brand_raw_examples": "Giorgio Armani",
    "product_line_raw_examples": "",
    "shade_raw_examples": "No. 6",
    "brand_standardized": "ARMANI Beauty",
    "brand_standardized_score": 95,
    "brand_match_status": "success"
  },
  {
    "canonical_video_id": "7096913425695018245",
    "video_url": "https://www.tiktok.com/@hanstluce/video/7096913425695018245",
    "source": "combined_transcript",
    "confidence": 3,
    "brand_clean": "Urban Decay",
    "product_line_clean": "Hydromaniac Glowy Tinted Hydrator Foundation",
    "shade_clean": "41",
    "brand_score": 100,
    "product_score": 85,
    "shade_score": 90,
    "shade_variant_used_for_match": "41 Light Medium",
    "brand_raw_examples": "Urban Decay",
    "product_line_raw_examples": "Tinted Glow",
    "shade_raw_examples": "41 Light Medium",
    "brand_standardized": "Urban Decay",
    "brand_standardized_score": 95,
    "brand_match_status": "success"
  },
  {
    "canonical_video_id": "7106978723139783979",
    "video_url": "https://www.tiktok.com/@jamescharles/video/7106978723139783979",
    "source": "combined_transcript",
    "confidence": 1,
    "brand_clean": "Beauty Pie",
    "product_line_clean": null,
    "shade_clean": null,
    "brand_score": 85,
    "product_score": 28,
    "shade_score": 0,
    "shade_variant_used_for_match": null,
    "brand_raw_examples": "Jones Road Beauty",
    "product_line_raw_examples": "What The Foundation",
    "shade_raw_examples": "beige",
    "brand_standardized": null,
    "brand_standardized_score": 0,
    "brand_match_status": "ai_returned_none"
  },
  {
    "canonical_video_id": "7136432031885528321",
    "video_url": "https://www.tiktok.com/@brookedarling7/video/7136432031885528321",
    "source": "combined_transcript",
    "confidence": 3,
    "brand_clean": "NARS",
    "product_line_clean": "Light Reflecting Foundation",
    "shade_clean": "Mont Blanc",
    "brand_score": 100,
    "product_score": 100,
    "shade_score": 95,
    "shade_variant_used_for_match": "Mount Blanc",
    "brand_raw_examples": "NARS",
    "product_line_raw_examples": "Light Reflecting Foundation",
    "shade_raw_examples": "Mount Blanc",
    "brand_standardized": "NARS",
    "brand_standardized_score": 95,
    "brand_match_status": "success"
  },
  {
    "canonical_video_id": "7137738237229108526",
    "video_url": "https://www.tiktok.com/@danessamyricksbeauty/video/7137738237229108526",
    "source": "combined_transcript",
    "confidence": 1,
    "brand_clean": null,
    "product_line_clean": null,
    "shade_clean": null,
    "brand_score": 0,
    "product_score": 0,
    "shade_score": 0,
    "shade_variant_used_for_match": null,
    "brand_raw_examples": "",
    "product_line_raw_examples": "universal",
    "shade_raw_examples": "universal",
    "brand_standardized": null,
    "brand_standardized_score": 0,
    "brand_match_status": "empty_input"
  },
  {
    "canonical_video_id": "7137738237229108526",
    "video_url": "https://www.tiktok.com/@danessamyricksbeauty/video/7137738237229108526",
    "source": "combined_transcript",
    "confidence": 1,
    "brand_clean": null,
    "product_line_clean": null,
    "shade_clean": null,
    "brand_score": 0,
    "product_score": 0,
    "shade_score": 0,
    "shade_variant_used_for_match": null,
    "brand_raw_examples": "",
    "product_line_raw_examples": "tinted shades",
    "shade_raw_examples": "shade 1",
    "brand_standardized": null,
    "brand_standardized_score": 0,
    "brand_match_status": "empty_input"
  },
  {
    "canonical_video_id": "7137738237229108526",
    "video_url": "https://www.tiktok.com/@danessamyricksbeauty/video/7137738237229108526",
    "source": "combined_transcript",
    "confidence": 1,
    "brand_clean": null,
    "product_line_clean": null,
    "shade_clean": null,
    "brand_score": 0,
    "product_score": 0,
    "shade_score": 0,
    "shade_variant_used_for_match": null,
    "brand_raw_examples": "",
    "product_line_raw_examples": "tinted shades",
    "shade_raw_examples": "shade 10",
    "brand_standardized": null,
    "brand_standardized_score": 0,
    "brand_match_status": "empty_input"
  },
  {
    "canonical_video_id": "7137738237229108526",
    "video_url": "https://www.tiktok.com/@danessamyricksbeauty/video/7137738237229108526",
    "source": "combined_transcript",
    "confidence": 1,
    "brand_clean": null,
    "product_line_clean": null,
    "shade_clean": null,
    "brand_score": 0,
    "product_score": 0,
    "shade_score": 0,
    "shade_variant_used_for_match": null,
    "brand_raw_examples": "",
    "product_line_raw_examples": "tinted shades",
    "shade_raw_examples": "shade 9",
    "brand_standardized": null,
    "brand_standardized_score": 0,
    "brand_match_status": "empty_input"
  },
  {
    "canonical_video_id": "7144834071460416814",
    "video_url": "https://www.tiktok.com/@jodiewoodss/video/7144834071460416814",
    "source": "combined_transcript",
    "confidence": 3,
    "brand_clean": "MAC",
    "product_line_clean": "MAC Studio Fix Powder Plus Foundation C30",
    "shade_clean": "C4",
    "brand_score": 100,
    "product_score": 85,
    "shade_score": 90,
    "shade_variant_used_for_match": "NC40",
    "brand_raw_examples": "MAC",
    "product_line_raw_examples": "Studio Fix Fluid Foundation",
    "shade_raw_examples": "NC40",
    "brand_standardized": "MAC",
    "brand_standardized_score": 95,
    "brand_match_status": "success"
  },
  {
    "canonical_video_id": "7145101324646976810",
    "video_url": "https://www.tiktok.com/@beccaleebeauty/video/7145101324646976810",
    "source": "combined_transcript",
    "confidence": 3,
    "brand_clean": "Estée Lauder",
    "product_line_clean": "Double Wear Stay in Place Matte Powder Foundation",
    "shade_clean": "4N1 Shell Beige",
    "brand_score": 96,
    "product_score": 95,
    "shade_score": 100,
    "shade_variant_used_for_match": "4N1 Shell Beige",
    "brand_raw_examples": "Estee Lauder",
    "product_line_raw_examples": "Double Wear Stay in Place Foundation",
    "shade_raw_examples": "4N1 Shell Beige",
    "brand_standardized": "Estée Lauder",
    "brand_standardized_score": 95,
    "brand_match_status": "success"
  },
  {
    "canonical_video_id": "7151401458959666437",
    "video_url": "https://www.tiktok.com/@esteepro_emmatillman/video/7151401458959666437",
    "source": "combined_transcript",
    "confidence": 3,
    "brand_clean": "Estée Lauder",
    "product_line_clean": "Double Wear Stay-in-Place Foundation",
    "shade_clean": "2N1 Desert Beige",
    "brand_score": 100,
    "product_score": 100,
    "shade_score": 100,
    "shade_variant_used_for_match": "2N1 Desert Beige",
    "brand_raw_examples": "Estée Lauder",
    "product_line_raw_examples": "Double Wear Stay-in-Place Foundation",
    "shade_raw_examples": "2N1 Desert Beige",
    "brand_standardized": "Estée Lauder",
    "brand_standardized_score": 95,
    "brand_match_status": "success"
  },
  {
    "canonical_video_id": "7151401458959666437",
    "video_url": "https://www.tiktok.com/@esteepro_emmatillman/video/7151401458959666437",
    "source": "combined_transcript",
    "confidence": 3,
    "brand_clean": "Estée Lauder",
    "product_line_clean": "Double Wear Stay-in-Place Foundation",
    "shade_clean": "2N2 Buff",
    "brand_score": 100,
    "product_score": 100,
    "shade_score": 100,
    "shade_variant_used_for_match": "2N2 Buff",
    "brand_raw_examples": "Estée Lauder",
    "product_line_raw_examples": "Double Wear Stay-in-Place Foundation",
    "shade_raw_examples": "2N2 Buff",
    "brand_standardized": "Estée Lauder",
    "brand_standardized_score": 95,
    "brand_match_status": "success"
  },
  {
    "canonical_video_id": "7183473972653083946",
    "video_url": "https://www.tiktok.com/@alexatoribio_/video/7183473972653083946",
    "source": "combined_transcript",
    "confidence": 1,
    "brand_clean": "BY MARIO",
    "product_line_clean": null,
    "shade_clean": null,
    "brand_score": 90,
    "product_score": 39,
    "shade_score": 0,
    "shade_variant_used_for_match": null,
    "brand_raw_examples": "Mario",
    "product_line_raw_examples": "Surreal Skin Foundation",
    "shade_raw_examples": "12-0",
    "brand_standardized": "MAKEUP BY MARIO",
    "brand_standardized_score": 95,
    "brand_match_status": "success"
  },
  {
    "canonical_video_id": "7183473972653083946",
    "video_url": "https://www.tiktok.com/@alexatoribio_/video/7183473972653083946",
    "source": "combined_transcript",
    "confidence": 3,
    "brand_clean": "Danessa Myricks Beauty",
    "product_line_clean": "Yummy Skin Serum Foundation",
    "shade_clean": "9N",
    "brand_score": 95,
    "product_score": 95,
    "shade_score": 100,
    "shade_variant_used_for_match": "9N",
    "brand_raw_examples": "Danessa Myricks",
    "product_line_raw_examples": "Yummy Skin Foundation",
    "shade_raw_examples": "9N",
    "brand_standardized": "Danessa Myricks Beauty",
    "brand_standardized_score": 95,
    "brand_match_status": "success"
  },
  {
    "canonical_video_id": "7208689093042261294",
    "video_url": "https://www.tiktok.com/@itsmyrayeraye/video/7208689093042261294",
    "source": "combined_transcript",
    "confidence": 2,
    "brand_clean": "L'Oréal",
    "product_line_clean": "Age Perfect Radiant Serum Foundation",
    "shade_clean": null,
    "brand_score": 93,
    "product_score": 85,
    "shade_score": 0,
    "shade_variant_used_for_match": null,
    "brand_raw_examples": "L'Oreal",
    "product_line_raw_examples": "True Match foundation",
    "shade_raw_examples": "W6",
    "brand_standardized": "L'Oréal Paris",
    "brand_standardized_score": 95,
    "brand_match_status": "success"
  },
  {
    "canonical_video_id": "7209741379294039302",
    "video_url": "https://www.tiktok.com/@emilietommerberg/video/7209741379294039302",
    "source": "combined_transcript",
    "confidence": 3,
    "brand_clean": "Armani Beauty",
    "product_line_clean": "Luminous Silk Hydrating Face and Under-Eye Concealer",
    "shade_clean": "2",
    "brand_score": 90,
    "product_score": 85,
    "shade_score": 90,
    "shade_variant_used_for_match": "525",
    "brand_raw_examples": "Armani",
    "product_line_raw_examples": "Luminous Silk Foundation",
    "shade_raw_examples": "525",
    "brand_standardized": "ARMANI Beauty",
    "brand_standardized_score": 95,
    "brand_match_status": "success"
  },
  {
    "canonical_video_id": "7209741379294039302",
    "video_url": "https://www.tiktok.com/@emilietommerberg/video/7209741379294039302",
    "source": "combined_transcript",
    "confidence": 3,
    "brand_clean": "Armani Beauty",
    "product_line_clean": "Luminous Silk Hydrating Face and Under-Eye Concealer",
    "shade_clean": "5",
    "brand_score": 90,
    "product_score": 85,
    "shade_score": 90,
    "shade_variant_used_for_match": "58",
    "brand_raw_examples": "Armani",
    "product_line_raw_examples": "Luminous Silk Foundation",
    "shade_raw_examples": "5.9 | 58 | 59",
    "brand_standardized": "ARMANI Beauty",
    "brand_standardized_score": 95,
    "brand_match_status": "success"
  },
  {
    "canonical_video_id": "7209741379294039302",
    "video_url": "https://www.tiktok.com/@emilietommerberg/video/7209741379294039302",
    "source": "combined_transcript",
    "confidence": 3,
    "brand_clean": "Armani Beauty",
    "product_line_clean": "Luminous Silk Hydrating Face and Under-Eye Concealer",
    "shade_clean": "6",
    "brand_score": 90,
    "product_score": 85,
    "shade_score": 100,
    "shade_variant_used_for_match": "6",
    "brand_raw_examples": "Armani",
    "product_line_raw_examples": "Luminous Silk Foundation",
    "shade_raw_examples": "6",
    "brand_standardized": "ARMANI Beauty",
    "brand_standardized_score": 95,
    "brand_match_status": "success"
  },
  {
    "canonical_video_id": "7209741379294039302",
    "video_url": "https://www.tiktok.com/@emilietommerberg/video/7209741379294039302",
    "source": "combined_transcript",
    "confidence": 3,
    "brand_clean": "Armani Beauty",
    "product_line_clean": "Luminous Silk Hydrating Face and Under-Eye Concealer",
    "shade_clean": "5.25",
    "brand_score": 90,
    "product_score": 85,
    "shade_score": 100,
    "shade_variant_used_for_match": "5.25",
    "brand_raw_examples": "Armani",
    "product_line_raw_examples": "Luminous Silk Foundation",
    "shade_raw_examples": "5.25",
    "brand_standardized": "ARMANI Beauty",
    "brand_standardized_score": 95,
    "brand_match_status": "success"
  },
  {
    "canonical_video_id": "7212617151386045702",
    "video_url": "https://www.tiktok.com/@goose_katai/video/7212617151386045702",
    "source": "combined_transcript",
    "confidence": 3,
    "brand_clean": "Dior",
    "product_line_clean": "Dior Forever Fluid Skin Glow Foundation",
    "shade_clean": "4.5N Neutral",
    "brand_score": 100,
    "product_score": 95,
    "shade_score": 95,
    "shade_variant_used_for_match": "4.5 Neutral",
    "brand_raw_examples": "Dior",
    "product_line_raw_examples": "Forever Skin Glow Foundation",
    "shade_raw_examples": "4.5 Neutral",
    "brand_standardized": "DIOR",
    "brand_standardized_score": 95,
    "brand_match_status": "success"
  },
  {
    "canonical_video_id": "7216263673315085573",
    "video_url": "https://www.tiktok.com/@kimmmann_/video/7216263673315085573",
    "source": "combined_transcript",
    "confidence": 1,
    "brand_clean": "MAC",
    "product_line_clean": null,
    "shade_clean": null,
    "brand_score": 100,
    "product_score": 0,
    "shade_score": 0,
    "shade_variant_used_for_match": null,
    "brand_raw_examples": "MAC",
    "product_line_raw_examples": "",
    "shade_raw_examples": "NC42",
    "brand_standardized": "MAC",
    "brand_standardized_score": 95,
    "brand_match_status": "success"
  },
  {
    "canonical_video_id": "7216263673315085573",
    "video_url": "https://www.tiktok.com/@kimmmann_/video/7216263673315085573",
    "source": "combined_transcript",
    "confidence": 1,
    "brand_clean": null,
    "product_line_clean": null,
    "shade_clean": null,
    "brand_score": 0,
    "product_score": 0,
    "shade_score": 0,
    "shade_variant_used_for_match": null,
    "brand_raw_examples": "Essay Lauder",
    "product_line_raw_examples": "",
    "shade_raw_examples": "3W2 Cashew",
    "brand_standardized": "Estée Lauder",
    "brand_standardized_score": 95,
    "brand_match_status": "success"
  },
  {
    "canonical_video_id": "7216263673315085573",
    "video_url": "https://www.tiktok.com/@kimmmann_/video/7216263673315085573",
    "source": "combined_transcript",
    "confidence": 1,
    "brand_clean": null,
    "product_line_clean": null,
    "shade_clean": null,
    "brand_score": 0,
    "product_score": 0,
    "shade_score": 0,
    "shade_variant_used_for_match": null,
    "brand_raw_examples": "Essay Lauder",
    "product_line_raw_examples": "",
    "shade_raw_examples": "4W1 Honey Bronze",
    "brand_standardized": "Estée Lauder",
    "brand_standardized_score": 95,
    "brand_match_status": "success"
  },
  {
    "canonical_video_id": "7216263673315085573",
    "video_url": "https://www.tiktok.com/@kimmmann_/video/7216263673315085573",
    "source": "combined_transcript",
    "confidence": 2,
    "brand_clean": "NARS",
    "product_line_clean": "Light Reflecting Foundation",
    "shade_clean": null,
    "brand_score": 100,
    "product_score": 100,
    "shade_score": 0,
    "shade_variant_used_for_match": null,
    "brand_raw_examples": "NARS",
    "product_line_raw_examples": "Light Reflecting Foundation",
    "shade_raw_examples": "Vanity M3.5",
    "brand_standardized": "NARS",
    "brand_standardized_score": 95,
    "brand_match_status": "success"
  },
  {
    "canonical_video_id": "7216263673315085573",
    "video_url": "https://www.tiktok.com/@kimmmann_/video/7216263673315085573",
    "source": "combined_transcript",
    "confidence": 3,
    "brand_clean": "Lancôme",
    "product_line_clean": "Lancôme Renergie Lift Makeup Foundation - Lightweight & Hydrating Formula, Medium-Full Coverage, SPF 27, Anti-Aging, Lifting & Firming, Up to 12H Wear",
    "shade_clean": "420",
    "brand_score": 93,
    "product_score": 85,
    "shade_score": 85,
    "shade_variant_used_for_match": "420W",
    "brand_raw_examples": "Lancome",
    "product_line_raw_examples": "Tintidot Ultra Wear",
    "shade_raw_examples": "420W",
    "brand_standardized": "Lancôme",
    "brand_standardized_score": 95,
    "brand_match_status": "success"
  },
  {
    "canonical_video_id": "7217950796611161349",
    "video_url": "https://www.tiktok.com/@bymoniquepineda/video/7217950796611161349",
    "source": "combined_transcript",
    "confidence": 1,
    "brand_clean": "Rare Beauty by Selena Gomez",
    "product_line_clean": null,
    "shade_clean": null,
    "brand_score": 90,
    "product_score": 0,
    "shade_score": 0,
    "shade_variant_used_for_match": null,
    "brand_raw_examples": "Rare Beauty",
    "product_line_raw_examples": "",
    "shade_raw_examples": "280",
    "brand_standardized": "Rare Beauty by Selena Gomez",
    "brand_standardized_score": 95,
    "brand_match_status": "success"
  },
  {
    "canonical_video_id": "7221239604727303430",
    "video_url": "https://www.tiktok.com/@kikeaj_/video/7221239604727303430",
    "source": "combined_transcript",
    "confidence": 1,
    "brand_clean": "MAC",
    "product_line_clean": null,
    "shade_clean": null,
    "brand_score": 100,
    "product_score": 0,
    "shade_score": 0,
    "shade_variant_used_for_match": null,
    "brand_raw_examples": "MAC",
    "product_line_raw_examples": "",
    "shade_raw_examples": "NW50",
    "brand_standardized": "MAC",
    "brand_standardized_score": 95,
    "brand_match_status": "success"
  },
  {
    "canonical_video_id": "7224190890972024110",
    "video_url": "https://www.tiktok.com/@kensnation/video/7224190890972024110",
    "source": "combined_transcript",
    "confidence": 2,
    "brand_clean": "Estée Lauder",
    "product_line_clean": "Double Wear Max Cover Camouflage Foundation For Face and Body SPF 15",
    "shade_clean": null,
    "brand_score": 96,
    "product_score": 85,
    "shade_score": 0,
    "shade_variant_used_for_match": null,
    "brand_raw_examples": "Estee Lauder",
    "product_line_raw_examples": "Double Wear foundation",
    "shade_raw_examples": "Sand",
    "brand_standardized": "Estée Lauder",
    "brand_standardized_score": 95,
    "brand_match_status": "success"
  },
  {
    "canonical_video_id": "7234313152794496261",
    "video_url": "https://www.tiktok.com/@carmencamposa/video/7234313152794496261",
    "source": "combined_transcript",
    "confidence": 1,
    "brand_clean": "stila",
    "product_line_clean": null,
    "shade_clean": null,
    "brand_score": 90,
    "product_score": 45,
    "shade_score": 0,
    "shade_variant_used_for_match": null,
    "brand_raw_examples": "Stilauder",
    "product_line_raw_examples": "Double Wear Stay in Place",
    "shade_raw_examples": "4N2 Spice Sand",
    "brand_standardized": "stila",
    "brand_standardized_score": 95,
    "brand_match_status": "success"
  },
  {
    "canonical_video_id": "7235073720514055470",
    "video_url": "https://www.tiktok.com/@vandanikn/video/7235073720514055470",
    "source": "combined_transcript",
    "confidence": 2,
    "brand_clean": "Estée Lauder",
    "product_line_clean": "Double Wear Max Cover Camouflage Foundation For Face and Body SPF 15",
    "shade_clean": null,
    "brand_score": 96,
    "product_score": 85,
    "shade_score": 0,
    "shade_variant_used_for_match": null,
    "brand_raw_examples": "Estee Lauder",
    "product_line_raw_examples": "Double Wear foundation",
    "shade_raw_examples": "3W1.5 Fawn",
    "brand_standardized": "Estée Lauder",
    "brand_standardized_score": 95,
    "brand_match_status": "success"
  },
  {
    "canonical_video_id": "7235073720514055470",
    "video_url": "https://www.tiktok.com/@vandanikn/video/7235073720514055470",
    "source": "combined_transcript",
    "confidence": 2,
    "brand_clean": "Estée Lauder",
    "product_line_clean": "Double Wear Max Cover Camouflage Foundation For Face and Body SPF 15",
    "shade_clean": null,
    "brand_score": 96,
    "product_score": 85,
    "shade_score": 0,
    "shade_variant_used_for_match": null,
    "brand_raw_examples": "Estee Lauder",
    "product_line_raw_examples": "Double Wear foundation",
    "shade_raw_examples": "3W1.5 Fawn",
    "brand_standardized": "Estée Lauder",
    "brand_standardized_score": 95,
    "brand_match_status": "success"
  },
  {
    "canonical_video_id": "7235073720514055470",
    "video_url": "https://www.tiktok.com/@vandanakan/video/7235073720514055470",
    "source": "combined_transcript",
    "confidence": 2,
    "brand_clean": "Estée Lauder",
    "product_line_clean": "Double Wear Max Cover Camouflage Foundation For Face and Body SPF 15",
    "shade_clean": null,
    "brand_score": 96,
    "product_score": 85,
    "shade_score": 0,
    "shade_variant_used_for_match": null,
    "brand_raw_examples": "Estee Lauder",
    "product_line_raw_examples": "Double Wear foundation",
    "shade_raw_examples": "3W1.5 Fawn",
    "brand_standardized": "Estée Lauder",
    "brand_standardized_score": 95,
    "brand_match_status": "success"
  },
  {
    "canonical_video_id": "7235073720514055470",
    "video_url": "https://www.tiktok.com/@vandanakan/video/7235073720514055470",
    "source": "combined_transcript",
    "confidence": 2,
    "brand_clean": "Estée Lauder",
    "product_line_clean": "Double Wear Max Cover Camouflage Foundation For Face and Body SPF 15",
    "shade_clean": null,
    "brand_score": 96,
    "product_score": 85,
    "shade_score": 0,
    "shade_variant_used_for_match": null,
    "brand_raw_examples": "Estee Lauder",
    "product_line_raw_examples": "Double Wear foundation",
    "shade_raw_examples": "3W1.5 Fawn",
    "brand_standardized": "Estée Lauder",
    "brand_standardized_score": 95,
    "brand_match_status": "success"
  },
  {
    "canonical_video_id": "7247575591266897198",
    "video_url": "https://www.tiktok.com/@claudnutt/video/7247575591266897198",
    "source": "combined_transcript",
    "confidence": 2,
    "brand_clean": "Estée Lauder",
    "product_line_clean": "Double Wear Max Cover Camouflage Foundation For Face and Body SPF 15",
    "shade_clean": null,
    "brand_score": 96,
    "product_score": 90,
    "shade_score": 0,
    "shade_variant_used_for_match": null,
    "brand_raw_examples": "Estee Lauder",
    "product_line_raw_examples": "foundation",
    "shade_raw_examples": "3W1",
    "brand_standardized": "Estée Lauder",
    "brand_standardized_score": 95,
    "brand_match_status": "success"
  },
  {
    "canonical_video_id": "7247575591266897198",
    "video_url": "https://www.tiktok.com/@claudnutt/video/7247575591266897198",
    "source": "combined_transcript",
    "confidence": 1,
    "brand_clean": null,
    "product_line_clean": null,
    "shade_clean": null,
    "brand_score": 0,
    "product_score": 0,
    "shade_score": 0,
    "shade_variant_used_for_match": null,
    "brand_raw_examples": "Born This Way",
    "product_line_raw_examples": "foundation",
    "shade_raw_examples": "Warm Beige",
    "brand_standardized": "Too Faced",
    "brand_standardized_score": 100,
    "brand_match_status": "manual_correction"
  },
  {
    "canonical_video_id": "7247575591266897198",
    "video_url": "https://www.tiktok.com/@claudnutt/video/7247575591266897198",
    "source": "combined_transcript",
    "confidence": 2,
    "brand_clean": "MAC",
    "product_line_clean": "MAC Studio Fix Fluid SPF15 NC25",
    "shade_clean": null,
    "brand_score": 100,
    "product_score": 85,
    "shade_score": 0,
    "shade_variant_used_for_match": null,
    "brand_raw_examples": "MAC",
    "product_line_raw_examples": "Studio Sculpt",
    "shade_raw_examples": "NC37",
    "brand_standardized": "MAC",
    "brand_standardized_score": 95,
    "brand_match_status": "success"
  },
  {
    "canonical_video_id": "7247575591266897198",
    "video_url": "https://www.tiktok.com/@claudnutt/video/7247575591266897198",
    "source": "combined_transcript",
    "confidence": 3,
    "brand_clean": "HAUS LABS BY LADY GAGA",
    "product_line_clean": "Triclone Skin Tech Medium Coverage Foundation with Fermented Arnica",
    "shade_clean": "270 Light Medium Neutral",
    "brand_score": 85,
    "product_score": 90,
    "shade_score": 90,
    "shade_variant_used_for_match": "270",
    "brand_raw_examples": "Hoss Labs",
    "product_line_raw_examples": "foundation",
    "shade_raw_examples": "270",
    "brand_standardized": null,
    "brand_standardized_score": 0,
    "brand_match_status": "ai_returned_none"
  },
  {
    "canonical_video_id": "7247575591266897198",
    "video_url": "https://www.tiktok.com/@claudnutt/video/7247575591266897198",
    "source": "combined_transcript",
    "confidence": 2,
    "brand_clean": "NARS",
    "product_line_clean": "NARS Soft Matte Advanced Perfecting Powder 0.31oz/9g (Bay)",
    "shade_clean": null,
    "brand_score": 100,
    "product_score": 90,
    "shade_score": 0,
    "shade_variant_used_for_match": null,
    "brand_raw_examples": "NARS",
    "product_line_raw_examples": "Soft Matte",
    "shade_raw_examples": "Medium 3 Stramboli",
    "brand_standardized": "NARS",
    "brand_standardized_score": 95,
    "brand_match_status": "success"
  },
  {
    "canonical_video_id": "7250599406335135022",
    "video_url": "https://www.tiktok.com/@_boussoo/video/7250599406335135022",
    "source": "combined_transcript",
    "confidence": 1,
    "brand_clean": "stila",
    "product_line_clean": null,
    "shade_clean": null,
    "brand_score": 90,
    "product_score": 37,
    "shade_score": 0,
    "shade_variant_used_for_match": null,
    "brand_raw_examples": "Stilauder",
    "product_line_raw_examples": "Double Wear Stay-in-Place foundation",
    "shade_raw_examples": "C1 Rich Java",
    "brand_standardized": "stila",
    "brand_standardized_score": 95,
    "brand_match_status": "success"
  },
  {
    "canonical_video_id": "7257390303487757574",
    "video_url": "https://www.tiktok.com/@karlacruzbeauty/video/7257390303487757574",
    "source": "combined_transcript",
    "confidence": 3,
    "brand_clean": "Charlotte Tilbury",
    "product_line_clean": "Airbrush Flawless Foundation",
    "shade_clean": "5 Neutral",
    "brand_score": 100,
    "product_score": 100,
    "shade_score": 90,
    "shade_variant_used_for_match": "7.5 Neutral",
    "brand_raw_examples": "Charlotte Tilbury",
    "product_line_raw_examples": "Airbrush Flawless Foundation",
    "shade_raw_examples": "7.5 Neutral",
    "brand_standardized": "Charlotte Tilbury",
    "brand_standardized_score": 95,
    "brand_match_status": "success"
  },
  {
    "canonical_video_id": "7257390303487757574",
    "video_url": "https://www.tiktok.com/@karlacruzbeauty/video/7257390303487757574",
    "source": "combined_transcript",
    "confidence": 1,
    "brand_clean": "HAUS LABS BY LADY GAGA",
    "product_line_clean": null,
    "shade_clean": null,
    "brand_score": 85,
    "product_score": 0,
    "shade_score": 0,
    "shade_variant_used_for_match": null,
    "brand_raw_examples": "House Labs",
    "product_line_raw_examples": "",
    "shade_raw_examples": "260 Light Medium Cool",
    "brand_standardized": "HAUS LABS BY LADY GAGA",
    "brand_standardized_score": 95,
    "brand_match_status": "success"
  },
  {
    "canonical_video_id": "7257390303487757574",
    "video_url": "https://www.tiktok.com/@karlacruzbeauty/video/7257390303487757574",
    "source": "combined_transcript",
    "confidence": 3,
    "brand_clean": "Armani Beauty",
    "product_line_clean": "Luminous Silk Hydrating Face and Under-Eye Concealer",
    "shade_clean": "5.75",
    "brand_score": 90,
    "product_score": 90,
    "shade_score": 100,
    "shade_variant_used_for_match": "5.75",
    "brand_raw_examples": "Armani",
    "product_line_raw_examples": "Luminous Silk",
    "shade_raw_examples": "5.75",
    "brand_standardized": "ARMANI Beauty",
    "brand_standardized_score": 95,
    "brand_match_status": "success"
  },
  {
    "canonical_video_id": "7257390303487757574",
    "video_url": "https://www.tiktok.com/@karlacruzbeauty/video/7257390303487757574",
    "source": "combined_transcript",
    "confidence": 1,
    "brand_clean": null,
    "product_line_clean": null,
    "shade_clean": null,
    "brand_score": 0,
    "product_score": 0,
    "shade_score": 0,
    "shade_variant_used_for_match": null,
    "brand_raw_examples": "YSL",
    "product_line_raw_examples": "All Hours Foundation",
    "shade_raw_examples": "MN5",
    "brand_standardized": "Yves Saint Laurent",
    "brand_standardized_score": 95,
    "brand_match_status": "success"
  },
  {
    "canonical_video_id": "7257390303487757574",
    "video_url": "https://www.tiktok.com/@karlacruzbeauty/video/7257390303487757574",
    "source": "combined_transcript",
    "confidence": 1,
    "brand_clean": "Valentino",
    "product_line_clean": null,
    "shade_clean": null,
    "brand_score": 90,
    "product_score": 50,
    "shade_score": 0,
    "shade_variant_used_for_match": null,
    "brand_raw_examples": "Very Valentino",
    "product_line_raw_examples": "Light Lasting Perfecting Foundation",
    "shade_raw_examples": "MN4",
    "brand_standardized": "Valentino",
    "brand_standardized_score": 95,
    "brand_match_status": "success"
  },
  {
    "canonical_video_id": "7264621691270188321",
    "video_url": "https://www.tiktok.com/@anchalxx/video/7264621691270188321",
    "source": "combined_transcript",
    "confidence": 3,
    "brand_clean": "HOURGLASS",
    "product_line_clean": "Veil Hydrating Skin Tint",
    "shade_clean": "10",
    "brand_score": 100,
    "product_score": 100,
    "shade_score": 100,
    "shade_variant_used_for_match": "10",
    "brand_raw_examples": "Hourglass",
    "product_line_raw_examples": "Veil Hydrating Skin Tint",
    "shade_raw_examples": "10",
    "brand_standardized": "HOURGLASS",
    "brand_standardized_score": 95,
    "brand_match_status": "success"
  },
  {
    "canonical_video_id": "7265709481395309856",
    "video_url": "https://www.tiktok.com/@anousshkaaa/video/7265709481395309856",
    "source": "combined_transcript",
    "confidence": 2,
    "brand_clean": "NARS",
    "product_line_clean": "NARS Pure Radiant Tinted Moisturizer Broad Spectrum SPF 30, Terre Neuve",
    "shade_clean": null,
    "brand_score": 100,
    "product_score": 90,
    "shade_score": 0,
    "shade_variant_used_for_match": null,
    "brand_raw_examples": "NARS",
    "product_line_raw_examples": "Tinted Moisturizer",
    "shade_raw_examples": "Santiago",
    "brand_standardized": "NARS",
    "brand_standardized_score": 95,
    "brand_match_status": "success"
  },
  {
    "canonical_video_id": "7265709481395309856",
    "video_url": "https://www.tiktok.com/@anousshkaaa/video/7265709481395309856",
    "source": "combined_transcript",
    "confidence": 3,
    "brand_clean": "NARS",
    "product_line_clean": "Light Reflecting Foundation",
    "shade_clean": "Aruba",
    "brand_score": 100,
    "product_score": 100,
    "shade_score": 100,
    "shade_variant_used_for_match": "Aruba",
    "brand_raw_examples": "NARS",
    "product_line_raw_examples": "Light Reflecting Foundation",
    "shade_raw_examples": "Aruba",
    "brand_standardized": "NARS",
    "brand_standardized_score": 95,
    "brand_match_status": "success"
  },
  {
    "canonical_video_id": "7265709481395309856",
    "video_url": "https://www.tiktok.com/@anousshkaaa/video/7265709481395309856",
    "source": "combined_transcript",
    "confidence": 2,
    "brand_clean": "NARS",
    "product_line_clean": "NARS Sheer Glow Foundation, Gobi",
    "shade_clean": null,
    "brand_score": 100,
    "product_score": 90,
    "shade_score": 0,
    "shade_variant_used_for_match": null,
    "brand_raw_examples": "NARS",
    "product_line_raw_examples": "Sheer Glow",
    "shade_raw_examples": "Tahoe",
    "brand_standardized": "NARS",
    "brand_standardized_score": 95,
    "brand_match_status": "success"
  }
]